angel_master
