Metadata-Version: 1.1
Name: angel-master
Version: 1.1.0
Summary: The master of a distribute job scheduler named 'angel'
Home-page: https://pypi.python.org/pypi/angel_master
Author: Lafite93
Author-email: 2273337844@qq.com
License: Apache
Keywords: angel master
Platform: Linux
Platform: Unix
Classifier: Programming Language :: Python :: 3
Classifier: Programming Language :: Python :: 3.5
